hyperliquid_mcp/__init__.py
hyperliquid_mcp/logging_config.py
hyperliquid_mcp/models.py
hyperliquid_mcp/server.py
hyperliquid_mcp/tools/__init__.py
hyperliquid_mcp/tools/account.py
hyperliquid_mcp/tools/base_client.py
hyperliquid_mcp/tools/market.py
hyperliquid_mcp/tools/order.py
hyperliquid_mcp-1.0.3.dist-info/METADATA
hyperliquid_mcp-1.0.3.dist-info/WHEEL
hyperliquid_mcp-1.0.3.dist-info/entry_points.txt
hyperliquid_mcp-1.0.3.dist-info/licenses/LICENSE
hyperliquid_mcp-1.0.3.dist-info/RECORD
