Metadata-Version: 2.4
Name: hyperliquid-mcp
Version: 1.0.3
Summary: A server that exposes a set of tools for interacting with the Hyperliquid decentralized exchange. It simplifies trading operations by providing a high-level API for placing, canceling, and modifying orders, as well as managing account settings and retrieving market data.
Project-URL: Homepage, https://github.com/midodimori/hyperliquid-mcp
Project-URL: Repository, https://github.com/midodimori/hyperliquid-mcp
Project-URL: Issues, https://github.com/midodimori/hyperliquid-mcp/issues
Project-URL: Documentation, https://github.com/midodimori/hyperliquid-mcp#readme
Author-email: Minh DOAN <midogax272@gmail.com>
License: MIT License
License-File: LICENSE
Keywords: crypto,defi,exchange,hyperliquid,mcp,trading
Classifier: Development Status :: 4 - Beta
Classifier: Intended Audience :: Developers
Classifier: License :: OSI Approved :: MIT License
Classifier: Operating System :: OS Independent
Classifier: Programming Language :: Python :: 3
Classifier: Programming Language :: Python :: 3.13
Classifier: Topic :: Office/Business :: Financial :: Investment
Classifier: Topic :: Software Development :: Libraries :: Python Modules
Requires-Python: >=3.11
Requires-Dist: asyncio-throttle>=1.0.2
Requires-Dist: eth-account>=0.13.7
Requires-Dist: fastmcp>=2.10.6
Requires-Dist: hyperliquid-python-sdk>=0.16.0
Requires-Dist: pydantic>=2.11.7
Requires-Dist: python-dotenv>=1.1.1
Provides-Extra: dev
Requires-Dist: black>=25.1.0; extra == 'dev'
Requires-Dist: isort>=6.0.1; extra == 'dev'
Requires-Dist: mcp[cli]>=1.12.2; extra == 'dev'
Requires-Dist: mypy>=1.17.0; extra == 'dev'
Requires-Dist: pytest-asyncio>=1.1.0; extra == 'dev'
Requires-Dist: pytest-cov>=6.0.0; extra == 'dev'
Requires-Dist: pytest-mock>=3.14.1; extra == 'dev'
Requires-Dist: pytest>=8.4.1; extra == 'dev'
Requires-Dist: python-dotenv>=1.1.1; extra == 'dev'
Requires-Dist: ruff>=0.12.5; extra == 'dev'
